tag_text_extractor/__init__.py
tag_text_extractor/exceptions.py
tag_text_extractor/tag_text_extractor.py
tag_text_extractor/text_handler.py
tag_text_extractor-0.0.23.dist-info/METADATA
tag_text_extractor-0.0.23.dist-info/WHEEL
tag_text_extractor-0.0.23.dist-info/top_level.txt
tag_text_extractor-0.0.23.dist-info/RECORD
